__init__.py
clickactions/__init__.py
clickactions/command/__init__.py
clickactions/command/py_debug.py
clickactions/example/__init__.py
clickactions/example/echo/__init__.py
clickactions/example/echo/echo_command.py
clickactions/example/echo/echo_commands.py
clickactions/tmp/using_actions_logger.py
clickactions-0.1.1.dist-info/METADATA
clickactions-0.1.1.dist-info/WHEEL
clickactions-0.1.1.dist-info/entry_points.txt
clickactions-0.1.1.dist-info/top_level.txt
clickactions-0.1.1.dist-info/RECORD
